caption_contest_data/__init__.py
caption_contest_data/_api.py
caption_contest_data/_raw.py
caption_contest_data/_web.py
caption_contest_data/tests/__init__.py
caption_contest_data/tests/test_api.py
caption_contest_data/tests/test_process_raw_dashboards.py
caption_contest_data/tests/test_raw_dashboards.py
caption_contest_data/tests/test_responses.py
caption_contest_data-0.1.0.dist-info/LICENSE.txt
caption_contest_data-0.1.0.dist-info/METADATA
caption_contest_data-0.1.0.dist-info/WHEEL
caption_contest_data-0.1.0.dist-info/top_level.txt
caption_contest_data-0.1.0.dist-info/RECORD
